{
  "poll": [
    { "id" : "WW103T",
      "question" : [
        { "no": 1, "text": "How was WW103T question 1?",
          "answer": [
            { "pos": 0, "text": "It's answer 1" },
            { "pos": 1, "text": "It's answer 2" },
            { "pos": 2, "text": "It's answer 3" }
          ]
        },
        { "no": 2, "text": "How is question 2?",
          "answer": [
            { "pos": 0, "text": "It's answer 1" },
            { "pos": 1, "text": "It's answer 2" },
            { "pos": 2, "text": "It's answer 3" }
          ]
        },
        { "no": 3, "text": "What do you think of question 3?",
          "answer": [
            { "pos": 0, "text": "It's answer 1" },
            { "pos": 1, "text": "It's answer 2" },
            { "pos": 2, "text": "It's answer 3" }
          ]
        }
      ]
    },
    { "id" : "RC104T",
      "question" : [
        { "no": 1, "text": "How about RC104T question 1?",
          "answer": [
            { "pos": 0, "text": "It's answer 1" },
            { "pos": 1, "text": "It's answer 2" },
            { "pos": 2, "text": "It's answer 3" }
          ]
        },
        { "no": 2, "text": "Did you like question 2?",
          "answer": [
            { "pos": 0, "text": "It's answer 1" },
            { "pos": 1, "text": "It's answer 2" },
            { "pos": 2, "text": "It's answer 3" }
          ]
        },
        { "no": 3, "text": "Is this question 3?",
          "answer": [
            { "pos": 0, "text": "It's answer 1" },
            { "pos": 1, "text": "It's answer 2" },
            { "pos": 2, "text": "It's answer 3" }
          ]
        }
      ]
    },
    { "id" : "BH106T",
      "question" : [
        { "no": 1, "text": "How was BH106T question 1?",
          "answer": [
            { "pos": 0, "text": "It's answer 1" },
            { "pos": 1, "text": "It's answer 2" },
            { "pos": 2, "text": "It's answer 3" }
          ]
        },
        { "no": 2, "text": "Was question 2 good?",
          "answer": [
            { "pos": 0, "text": "It's answer 1" },
            { "pos": 1, "text": "It's answer 2" },
            { "pos": 2, "text": "It's answer 3" }
          ]
        },
        { "no": 3, "text": "What about question 3?",
          "answer": [
            { "pos": 0, "text": "It's answer 1" },
            { "pos": 1, "text": "It's answer 2" },
            { "pos": 2, "text": "It's answer 3" }
          ]
        }
      ]
    }
  ]
}